StealthIM/__init__.py
StealthIM/group.py
StealthIM/server.py
StealthIM/user.py
StealthIM/apis/__init__.py
StealthIM/apis/common.py
StealthIM/apis/file.py
StealthIM/apis/group.py
StealthIM/apis/message.py
StealthIM/apis/user.py
StealthIM/apis/util.py
stealthimpysdk-0.1.6.dist-info/licenses/LICENSE
stealthimpysdk-0.1.6.dist-info/METADATA
stealthimpysdk-0.1.6.dist-info/WHEEL
stealthimpysdk-0.1.6.dist-info/top_level.txt
stealthimpysdk-0.1.6.dist-info/RECORD
