Metadata-Version: 2.4
Name: stealthimpysdk
Version: 0.1.6
Summary: The SDK for StealthIM
Author-email: Ken <keniis@126.com>
License: MIT License
Project-URL: Homepage, https://github.com/StealthIM/StealthIMPythonSDK
Requires-Python: >=3.9
License-File: LICENSE
Requires-Dist: aiohttp>=3.12.15
Requires-Dist: blake3==1.0.6
Dynamic: license-file
